{
  "user_id": "4cac07df-8832-4965-9693-e11ef0b5d11e",
  "interview_id": "97f05d3d-fac1-4497-8d39-2e47e1f4b6f4",
  "timestamp": "2025-08-06_23-18-59",
  "question": "병렬 처리 및 동시성을 고려한 코드를 개발한 경험이 있다면, 병목 현상을 최소화하기 위한 전략은 무엇이었나요?",
  "text": "잘 모르겠습니다",
  "emotion": "neutral",
  "probabilities": {
    "angry": 4.4792054723075125e-06,
    "disgust": 9.16253597438299e-08,
    "fear": 4.634266748126947e-09,
    "happiness": 1.2617932043212932e-05,
    "neutral": 0.999634861946106,
    "sadness": 0.0003475684206932783,
    "surprise": 3.388941252069344e-07
  }
}