{
  "user_id": "4cac07df-8832-4965-9693-e11ef0b5d11e",
  "interview_id": "f1c7cb93-2555-49cb-88d8-caca04e9b963",
  "timestamp": "2025-08-07_00-00-36",
  "question": "데이터 분석 프로젝트에서 어려움을 겪을 때 어떻게 해결하고, 결론을 도출하기 위해 어떤 방법을 사용했나요?",
  "text": "잘 모르겠습니다",
  "emotion": "neutral",
  "probabilities": {
    "angry": 0.00013519325875677168,
    "disgust": 0.0003825919411610812,
    "fear": 1.4985072084527928e-05,
    "happiness": 5.62260265724035e-06,
    "neutral": 0.9963594079017639,
    "sadness": 0.0030731249134987593,
    "surprise": 2.9122913474566303e-05
  }
}